backsub/CLI.py
backsub/__init__.py
backsub/__main__.py
backsub/_version.py
backsub/background_sub.py
backsub/metadata2markers.py
backsub/ome_schema.py
backsub/ome_writer.py
backsub-0.5.1.dist-info/licenses/LICENSE
backsub-0.5.1.dist-info/METADATA
backsub-0.5.1.dist-info/WHEEL
backsub-0.5.1.dist-info/entry_points.txt
backsub-0.5.1.dist-info/top_level.txt
backsub-0.5.1.dist-info/RECORD
