Metadata-Version: 2.4
Name: backsub
Version: 0.5.1
Summary: Channel subtraction scaled by exposure times
Author-email: Krešimir Bestak <kbestak@gmail.com>
License: MIT License
Project-URL: Homepage, https://github.com/schapirolabor/background_subtraction
Project-URL: Issues, https://github.com/schapirolabor/background_subtraction/issues
Keywords: autofluorescence,imaging,immunofluorescence,subtraction
Classifier: Intended Audience :: Science/Research
Classifier: Programming Language :: Python :: 3
Classifier: License :: OSI Approved :: MIT License
Requires-Python: >=3.9
License-File: LICENSE
Requires-Dist: pandas
Requires-Dist: tifffile
Requires-Dist: ome_types
Requires-Dist: numpy
Requires-Dist: loguru
Requires-Dist: dask
Requires-Dist: dask-image
Requires-Dist: scikit-image
Requires-Dist: zarr>=3
Dynamic: license-file
